ksherpay/__init__.py
ksherpay/constant.py
ksherpay/order.py
ksherpay/settlements.py
ksherpay/utils.py
ksherpay/test/__init__.py
ksherpay/test/test_create_order_bscanc.py
ksherpay/test/test_create_order_cscanb.py
ksherpay/test/test_create_order_finance.py
ksherpay/test/test_create_order_redirect.py
ksherpay-0.2.1.dist-info/LICENSE
ksherpay-0.2.1.dist-info/METADATA
ksherpay-0.2.1.dist-info/WHEEL
ksherpay-0.2.1.dist-info/top_level.txt
ksherpay-0.2.1.dist-info/zip-safe
ksherpay-0.2.1.dist-info/RECORD
