Metadata-Version: 2.1
Name: ksherpay
Version: 0.2.1
Summary: python implementation for Khser Payment API.
Home-page: https://github.com/ksher-solutions/payment_sdk_python
Author: Ksher
Author-email: support@ksher.com
License: MIT
Keywords: Ksher,ksher,ksher-payment,ksher-payment-api,ksherpay
Classifier: License :: OSI Approved :: MIT License
Classifier: Programming Language :: Python
Classifier: Programming Language :: Python :: 3.7
Classifier: Topic :: Software Development :: Libraries :: Python Modules
Classifier: Intended Audience :: Developers
Classifier: Operating System :: OS Independent
License-File: LICENSE
Requires-Dist: requests (>=2.25.1)
